src/__init__.py
src/__main__.py
src/cli.py
src/config.py
src/exceptions.py
src/instance_runner/__init__.py
src/instance_runner/api.py
src/instance_runner/claude_parser.py
src/instance_runner/codex_parser.py
src/instance_runner/docker_manager.py
src/instance_runner/git_operations.py
src/instance_runner/plugin_interface.py
src/instance_runner/runner.py
src/instance_runner/types.py
src/instance_runner/plugins/__init__.py
src/instance_runner/plugins/claude_code.py
src/instance_runner/plugins/codex.py
src/orchestration/__init__.py
src/orchestration/cli_parser.py
src/orchestration/event_bus.py
src/orchestration/orchestrator.py
src/orchestration/state.py
src/orchestration/strategy_context.py
src/orchestration/cli/__init__.py
src/orchestration/cli/auth.py
src/orchestration/cli/config_loader.py
src/orchestration/cli/config_print.py
src/orchestration/cli/doctor.py
src/orchestration/cli/headless.py
src/orchestration/cli/orchestrator_runner.py
src/orchestration/cli/parser_sections.py
src/orchestration/cli/preflight.py
src/orchestration/cli/results_display.py
src/orchestration/cli/runs.py
src/orchestration/cli/strategy_config.py
src/orchestration/cli/tui_runner.py
src/orchestration/cli/validation.py
src/orchestration/strategies/__init__.py
src/orchestration/strategies/base.py
src/orchestration/strategies/best_of_n.py
src/orchestration/strategies/bug_finding.py
src/orchestration/strategies/doc_review.py
src/orchestration/strategies/iterative.py
src/orchestration/strategies/loader.py
src/orchestration/strategies/pr_review.py
src/orchestration/strategies/scoring.py
src/orchestration/strategies/simple.py
src/shared/__init__.py
src/shared/types.py
src/tui/__init__.py
src/tui/__main__.py
src/tui/adaptive.py
src/tui/cli.py
src/tui/display.py
src/tui/event_handler.py
src/tui/models.py
src/utils/__init__.py
src/utils/log_rotation.py
src/utils/platform_utils.py
src/utils/structured_logging.py
pitaya-0.3.0.dist-info/METADATA
pitaya-0.3.0.dist-info/WHEEL
pitaya-0.3.0.dist-info/entry_points.txt
pitaya-0.3.0.dist-info/licenses/LICENSE
pitaya-0.3.0.dist-info/RECORD
