Metadata-Version: 2.4
Name: pitaya
Version: 0.3.0
Summary: Pitaya — an orchestrator of AI coding agents (e.g., Claude Code, Codex CLI) with pluggable and custom strategies
Project-URL: Repository, https://github.com/tact-lang/pitaya
Project-URL: Issues, https://github.com/tact-lang/pitaya/issues
Author: TON Studio
Maintainer: TON Studio
License: Copyright 2025 TON Studio
License-File: LICENSE
Keywords: agents,ai,automation,claude-code,codex-cli,coding,developer-tools,docker,orchestrator,tui
Classifier: Development Status :: 4 - Beta
Classifier: Environment :: Console
Classifier: Intended Audience :: Developers
Classifier: License :: OSI Approved :: MIT License
Classifier: Programming Language :: Python :: 3 :: Only
Classifier: Programming Language :: Python :: 3.13
Classifier: Topic :: Software Development :: Build Tools
Classifier: Topic :: Software Development :: Code Generators
Requires-Python: ==3.13.*
Requires-Dist: aiofiles>=24.1.0
Requires-Dist: click>=8.1.0
Requires-Dist: docker>=7.1.0
Requires-Dist: python-dotenv>=1.0.0
Requires-Dist: pyyaml>=6.0.2
Requires-Dist: rich>=14.0.0
Requires-Dist: typing-extensions>=4.12.0
Requires-Dist: watchdog>=6.0.0
